priori/__init__.py
priori/core.cp39-win_amd64.pyd
priori/docs/__init__.py
priori/docs/scripta.cp39-win_amd64.pyd
priori/docs/scripta.py
src/__init__.py
src/core.cp39-win_amd64.pyd
src/docs/__init__.py
src/docs/scripta.py
priori-0.0.2.dist-info/LICENSE
priori-0.0.2.dist-info/METADATA
priori-0.0.2.dist-info/WHEEL
priori-0.0.2.dist-info/top_level.txt
priori-0.0.2.dist-info/RECORD
