Metadata-Version: 2.1
Name: priori
Version: 0.0.2
Summary: scientific calculation toolkit
Home-page: https://github.com/CubicZebra/priori
Author: ChenZHANG
Author-email: chen.zhang_06sept@foxmail.com
Maintainer: ChenZHANG
Maintainer-email: chen.zhang_06sept@foxmail.com
License: 
Classifier: Development Status :: 4 - Beta
Classifier: Intended Audience :: Healthcare Industry
Classifier: Intended Audience :: Science/Research
Classifier: Intended Audience :: Developers
Classifier: Topic :: Scientific/Engineering :: Information Analysis
Classifier: License :: OSI Approved :: Apache Software License
Classifier: Programming Language :: Python :: 3
Classifier: Programming Language :: Python :: 3.7
Classifier: Programming Language :: Python :: 3.8
Classifier: Programming Language :: Python :: 3.9
Classifier: Programming Language :: Python :: 3.10
Requires-Python: >=3.7
License-File: LICENSE
